pydiverse/.gitignore
pydiverse/transform/__init__.py
pydiverse/transform/base.py
pydiverse/transform/common.py
pydiverse/transform/errors.py
pydiverse/transform/extended.py
pydiverse/transform/types.py
pydiverse/transform/version.py
pydiverse/transform/_internal/backend/duckdb.py
pydiverse/transform/_internal/backend/duckdb_polars.py
pydiverse/transform/_internal/backend/ibm_db2.py
pydiverse/transform/_internal/backend/impl_store.py
pydiverse/transform/_internal/backend/mssql.py
pydiverse/transform/_internal/backend/polars.py
pydiverse/transform/_internal/backend/postgres.py
pydiverse/transform/_internal/backend/sql.py
pydiverse/transform/_internal/backend/sqlalchemy_fixes.py
pydiverse/transform/_internal/backend/sqlite.py
pydiverse/transform/_internal/backend/table_impl.py
pydiverse/transform/_internal/backend/targets.py
pydiverse/transform/_internal/errors/__init__.py
pydiverse/transform/_internal/ops/op.py
pydiverse/transform/_internal/ops/signature.py
pydiverse/transform/_internal/ops/ops/__init__.py
pydiverse/transform/_internal/ops/ops/aggregation.py
pydiverse/transform/_internal/ops/ops/arithmetic.py
pydiverse/transform/_internal/ops/ops/comparison.py
pydiverse/transform/_internal/ops/ops/datetime.py
pydiverse/transform/_internal/ops/ops/horizontal.py
pydiverse/transform/_internal/ops/ops/list.py
pydiverse/transform/_internal/ops/ops/logical.py
pydiverse/transform/_internal/ops/ops/markers.py
pydiverse/transform/_internal/ops/ops/numeric.py
pydiverse/transform/_internal/ops/ops/string.py
pydiverse/transform/_internal/ops/ops/window.py
pydiverse/transform/_internal/pipe/aligned.py
pydiverse/transform/_internal/pipe/c.py
pydiverse/transform/_internal/pipe/cache.py
pydiverse/transform/_internal/pipe/functions.py
pydiverse/transform/_internal/pipe/pipeable.py
pydiverse/transform/_internal/pipe/table.py
pydiverse/transform/_internal/pipe/verbs.py
pydiverse/transform/_internal/tree/ast.py
pydiverse/transform/_internal/tree/col_expr.py
pydiverse_transform-0.7.0.dist-info/METADATA
pydiverse_transform-0.7.0.dist-info/WHEEL
pydiverse_transform-0.7.0.dist-info/licenses/LICENSE
pydiverse_transform-0.7.0.dist-info/RECORD
