Metadata-Version: 2.4
Name: pydiverse-transform
Version: 0.7.0
Summary: Pipe based dataframe manipulation library that can also transform data on SQL databases
Author: QuantCo, Inc.
Author-email: Nicolas Camenisch <garnele007@gmail.com>, Finn Rudolph <finn.rudolph@t-online.de>, Martin Trautmann <windiana@users.sf.net>
License: BSD 3-Clause License
License-File: LICENSE
Classifier: Development Status :: 4 - Beta
Classifier: Intended Audience :: Developers
Classifier: Intended Audience :: Science/Research
Classifier: License :: OSI Approved :: BSD License
Classifier: Programming Language :: Python :: 3
Classifier: Programming Language :: Python :: 3.11
Classifier: Programming Language :: Python :: 3.12
Classifier: Programming Language :: Python :: 3.13
Classifier: Programming Language :: Python :: 3.14
Classifier: Programming Language :: SQL
Classifier: Topic :: Database
Classifier: Topic :: Scientific/Engineering
Classifier: Topic :: Software Development
Requires-Python: <3.15.0a0,>=3.11.14
Requires-Dist: black>=20
Requires-Dist: pandas<3,>=2.3.0
Requires-Dist: polars<2,>=1.30.0
Requires-Dist: pyarrow<23,>=20.0.0
Requires-Dist: pydiverse-common<0.5,>=0.4.0
Requires-Dist: sqlalchemy<3,>=2.0.41
